itk/FixedPointInverseDisplacementFieldPython.py
itk/_FixedPointInverseDisplacementFieldPython.pyd
itk/itkFixedPointInverseDisplacementFieldImageFilterPython.py
itk/Configuration/FixedPointInverseDisplacementFieldConfig.py
itk_fixedpointinversedisplacementfield-1.0.0.dist-info/LICENSE
itk_fixedpointinversedisplacementfield-1.0.0.dist-info/METADATA
itk_fixedpointinversedisplacementfield-1.0.0.dist-info/WHEEL
itk_fixedpointinversedisplacementfield-1.0.0.dist-info/top_level.txt
itk_fixedpointinversedisplacementfield-1.0.0.dist-info/RECORD
